{
  "code": 200,
  "msg": "成功！",
  "data": {
    "cart": {
      "items": {
        "pdqsa9s8ecusv0cift4xdbndjargtaqs": {
          "product": {
            "id": "pdqsa9s8ecusv0cift4xdbndjargtaqs",
            "mlCategoryId": 1,
            "name": "辣条",
            "details": "非常好吃的辣条快来买吧",
            "price": 56.2,
            "stock": 8,
            "imgs": "http:///",
            "created": 1532628495000
          },
          "number": 3,
          "money": 168.60000000000002
        }
      },
      "totalNumber": 3,
      "totalMoney": 168.60000000000002
    }
  }
}